coti_safesync_framework/__init__.py
coti_safesync_framework/config.py
coti_safesync_framework/errors.py
coti_safesync_framework/signals.py
coti_safesync_framework/db/__init__.py
coti_safesync_framework/db/helpers.py
coti_safesync_framework/db/metrics.py
coti_safesync_framework/db/session.py
coti_safesync_framework/db/locking/__init__.py
coti_safesync_framework/db/locking/advisory_lock.py
coti_safesync_framework/db/locking/row_lock.py
coti_safesync_framework/metrics/__init__.py
coti_safesync_framework/metrics/registry.py
coti_safesync_framework/queue/__init__.py
coti_safesync_framework/queue/consumer.py
coti_safesync_framework/queue/metrics.py
coti_safesync_framework/queue/models.py
coti_safesync_framework/queue/redis_streams.py
coti_safesync_framework-0.0.2.dist-info/METADATA
coti_safesync_framework-0.0.2.dist-info/WHEEL
coti_safesync_framework-0.0.2.dist-info/top_level.txt
coti_safesync_framework-0.0.2.dist-info/RECORD
