Metadata-Version: 2.4
Name: coti-safesync-framework
Version: 0.0.2
Summary: Safe concurrent MySQL writes and Redis Streams queue operations
Author-email: COTI <dev@coti.io>
License: MIT
Classifier: Development Status :: 3 - Alpha
Classifier: Intended Audience :: Developers
Classifier: License :: OSI Approved :: MIT License
Classifier: Programming Language :: Python :: 3
Classifier: Programming Language :: Python :: 3.11
Classifier: Programming Language :: Python :: 3.12
Requires-Python: >=3.11
Requires-Dist: sqlalchemy>=2.0
Requires-Dist: redis>=5.0
Requires-Dist: prometheus-client>=0.19
Provides-Extra: dev
Requires-Dist: pytest>=7.0; extra == "dev"
Requires-Dist: pytest-cov>=4.0; extra == "dev"
Requires-Dist: black>=23.0; extra == "dev"
Requires-Dist: flake8>=6.0; extra == "dev"
Requires-Dist: mypy>=1.0; extra == "dev"
Requires-Dist: bandit>=1.0; extra == "dev"
Requires-Dist: safety>=2.0; extra == "dev"
Requires-Dist: pymysql>=1.0; extra == "dev"
